LICENSE
README.md
setup.py
aho/__init__.py
aho/__main__.py
aho/base.py
aho/bot.py
aho/cog_emoji.py
aho/cog_google_translate.py
aho/cog_mod.py
aho/cog_openai_chat.py
aho/cog_points.py
aho/cog_rng.py
aho/database.py
aho/general.py
aho/socket.py
aho/utils.py
aho.egg-info/PKG-INFO
aho.egg-info/SOURCES.txt
aho.egg-info/dependency_links.txt
aho.egg-info/entry_points.txt
aho.egg-info/requires.txt
aho.egg-info/top_level.txt