Metadata-Version: 2.1
Name: aho
Version: 1.3.2
Summary: aho - a Discord bot.
Home-page: https://gitlab.com/nul.one/aho
Download-URL: https://gitlab.com/nul.one/aho/-/archive/1.3.2/aho-1.3.2.tar.gz
Author: Predrag Mandic
Author-email: predrag@nul.one
License: BSD
Classifier: Development Status :: 4 - Beta
Classifier: Environment :: Console
Classifier: Intended Audience :: Developers
Classifier: Intended Audience :: Information Technology
Classifier: Intended Audience :: System Administrators
Classifier: Intended Audience :: Telecommunications Industry
Classifier: License :: OSI Approved :: BSD License
Classifier: Natural Language :: English
Classifier: Operating System :: POSIX :: Linux
Classifier: Programming Language :: Python :: 3 :: Only
Classifier: Natural Language :: English
Classifier: Topic :: Communications :: Chat
Classifier: Topic :: Games/Entertainment
Requires-Python: >=3.11.2
License-File: LICENSE
